reviewers/__init__.py
reviewers/__main__.py
blame_reviewers-0.1.1.dist-info/LICENSE
blame_reviewers-0.1.1.dist-info/METADATA
blame_reviewers-0.1.1.dist-info/WHEEL
blame_reviewers-0.1.1.dist-info/entry_points.txt
blame_reviewers-0.1.1.dist-info/top_level.txt
blame_reviewers-0.1.1.dist-info/RECORD
