Metadata-Version: 2.1
Name: blame-reviewers
Version: 0.1.1
Summary: CLI tool for searching code reviewers from git blame.
Home-page: UNKNOWN
Author: Evgeniy Baranov
License: MIT
Platform: UNKNOWN
Classifier: Programming Language :: Python
Classifier: Programming Language :: Python :: 3.7
Requires-Dist: sh (<2,>=1.12.13)
